LICENSE
MANIFEST.in
README.rst
metadata.py
setup.py
cmsplugin_search/__init__.py
cmsplugin_search/cms_app.py
cmsplugin_search/search_indexes.py
cmsplugin_search/settings.py
cmsplugin_search/utils.py
cmsplugin_search.egg-info/PKG-INFO
cmsplugin_search.egg-info/SOURCES.txt
cmsplugin_search.egg-info/dependency_links.txt
cmsplugin_search.egg-info/not-zip-safe
cmsplugin_search.egg-info/requires.txt
cmsplugin_search.egg-info/top_level.txt
cmsplugin_search/search_helpers/__init__.py
cmsplugin_search/search_helpers/fields.py
cmsplugin_search/search_helpers/indexes.py
cmsplugin_search/search_helpers/models.py
cmsplugin_search/search_helpers/templatetags/__init__.py
cmsplugin_search/search_helpers/templatetags/cms_search_tags.py