Metadata-Version: 1.1
Name: cmsplugin-search
Version: 0.8.0
Summary: An extension to django CMS to provide multilingual Haystack indexes (fork)
Home-page: https://gitlab.com/doctormo/cmsplugin-search
Author: Martin Owens via Divio GmbH
Author-email: doctormo@gmail.com
License: AGPLv3
Platform: OS Independent
Classifier: Framework :: Django
Classifier: Development Status :: 4 - Beta
Classifier: Intended Audience :: Developers
Classifier: License :: OSI Approved :: GNU Affero General Public License v3 or later (AGPLv3+)
Classifier: Operating System :: OS Independent
Classifier: Programming Language :: Python
Classifier: Topic :: Internet :: WWW/HTTP
